noinput_cli_mcp_server/__init__.py
noinput_cli_mcp_server/server.py
noinput_cli_mcp_server-0.0.1.dist-info/METADATA
noinput_cli_mcp_server-0.0.1.dist-info/WHEEL
noinput_cli_mcp_server-0.0.1.dist-info/entry_points.txt
noinput_cli_mcp_server-0.0.1.dist-info/licenses/LICENSE
noinput_cli_mcp_server-0.0.1.dist-info/licenses/NOTICE
noinput_cli_mcp_server-0.0.1.dist-info/RECORD
