Metadata-Version: 2.4
Name: noinput-cli-mcp-server
Version: 0.0.1
Summary: Command line interface for MCP clients with secure execution and customizable security policies (no STDIN)
Author: Amna AI/Run Team
Author-email: Mladen <fangs-lever6n@icloud.com>
License-File: LICENSE
License-File: NOTICE
Requires-Python: >=3.10
Requires-Dist: mcp>=1.6.0
